setup.cfg
setup.py
graphql_django_view/__init__.py
graphql_django_view.egg-info/PKG-INFO
graphql_django_view.egg-info/SOURCES.txt
graphql_django_view.egg-info/dependency_links.txt
graphql_django_view.egg-info/requires.txt
graphql_django_view.egg-info/top_level.txt